{
  "info": {
    "_postman_id": "a8c2c4d1-8dce-4b2a-b62a-8d1b1a4c8c7e",
    "name": "BTL_WEB",
    "schema": "https://schema.getpostman.com/json/collection/v2.1.0/collection.json"
  },
  "item": [
    {
      "name": "Auth",
      "item": [
        {
          "name": "Register",
          "request": {
            "method": "POST",
            "header": [],
            "body": {
              "mode": "raw",
              "raw": "{\n  \"name\": \"test user\",\n  \"email\": \"test@example.com\",\n  \"password\": \"password123\"\n}",
              "options": {
                "raw": {
                  "language": "json"
                }
              }
            },
            "url": {
              "raw": "{{base_url}}/auth/register",
              "host": [
                "{{base_url}}"
              ],
              "path": [
                "auth",
                "register"
              ]
            }
          },
          "response": []
        },
        {
          "name": "Login",
          "request": {
            "method": "POST",
            "header": [],
            "body": {
              "mode": "raw",
              "raw": "{\n  \"email\": \"test@example.com\",\n  \"password\": \"password123\"\n}",
              "options": {
                "raw": {
                  "language": "json"
                }
              }
            },
            "url": {
              "raw": "{{base_url}}/auth/login",
              "host": [
                "{{base_url}}"
              ],
              "path": [
                "auth",
                "login"
              ]
            }
          },
          "response": []
        },
        {
          "name": "Verify Phone",
          "request": {
            "method": "POST",
            "header": [],
            "body": {
              "mode": "raw",
              "raw": "{\n  \"phoneNumber\": \"+84394658369\"\n}",
              "options": {
                "raw": {
                  "language": "json"
                }
              }
            },
            "url": {
              "raw": "{{base_url}}/auth/verify-phone",
              "host": [
                "{{base_url}}"
              ],
              "path": [
                "auth",
                "verify-phone"
              ]
            }
          },
          "response": []
        },
        {
          "name": "Forgot Password",
          "request": {
            "method": "POST",
            "header": [],
            "body": {
              "mode": "raw",
              "raw": "{\n  \"email\": \"test@example.com\"\n}",
              "options": {
                "raw": {
                  "language": "json"
                }
              }
            },
            "url": {
              "raw": "{{base_url}}/auth/forgot-password",
              "host": [
                "{{base_url}}"
              ],
              "path": [
                "auth",
                "forgot-password"
              ]
            }
          },
          "response": []
        },
        {
          "name": "Reset Password",
          "request": {
            "method": "PATCH",
            "header": [],
            "body": {
              "mode": "raw",
              "raw": "{\n  \"password\": \"newpassword123\"\n}",
              "options": {
                "raw": {
                  "language": "json"
                }
              }
            },
            "url": {
              "raw": "{{base_url}}/auth/reset-password/:token",
              "host": [
                "{{base_url}}"
              ],
              "path": [
                "auth",
                "reset-password",
                ":token"
              ],
              "variable": [
                {
                  "key": "token",
                  "value": "some_reset_token"
                }
              ]
            }
          },
          "response": []
        }
      ]
    },
    {
      "name": "Author",
      "item": [
        {
          "name": "Create Author",
          "request": {
            "method": "POST",
            "header": [],
            "body": {
              "mode": "raw",
              "raw": "{\n  \"name\": \"New Author\",\n  \"biography\": \"A short bio of the new author.\"\n}",
              "options": {
                "raw": {
                  "language": "json"
                }
              }
            },
            "url": {
              "raw": "{{base_url}}/author",
              "host": [
                "{{base_url}}"
              ],
              "path": [
                "author"
              ]
            }
          },
          "response": []
        },
        {
          "name": "Get All Authors",
          "request": {
            "method": "GET",
            "header": [],
            "url": {
              "raw": "{{base_url}}/author",
              "host": [
                "{{base_url}}"
              ],
              "path": [
                "author"
              ]
            }
          },
          "response": []
        },
        {
          "name": "Get Author By Id",
          "request": {
            "method": "GET",
            "header": [],
            "url": {
              "raw": "{{base_url}}/author/some_author_id",
              "host": [
                "{{base_url}}"
              ],
              "path": [
                "author",
                "some_author_id"
              ]
            }
          },
          "response": []
        },
        {
          "name": "Update Author",
          "request": {
            "method": "PUT",
            "header": [],
            "body": {
              "mode": "raw",
              "raw": "{\n  \"name\": \"Updated Author Name\"\n}",
              "options": {
                "raw": {
                  "language": "json"
                }
              }
            },
            "url": {
              "raw": "{{base_url}}/author/some_author_id",
              "host": [
                "{{base_url}}"
              ],
              "path": [
                "author",
                "some_author_id"
              ]
            }
          },
          "response": []
        },
        {
          "name": "Delete Author",
          "request": {
            "method": "DELETE",
            "header": [],
            "url": {
              "raw": "{{base_url}}/author/some_author_id",
              "host": [
                "{{base_url}}"
              ],
              "path": [
                "author",
                "some_author_id"
              ]
            }
          },
          "response": []
        }
      ]
    },
    {
      "name": "Cart",
      "item": [
        {
          "name": "Get Cart",
          "request": {
            "method": "GET",
            "header": [
              {
                "key": "Authorization",
                "value": "Bearer {{auth_token}}"
              }
            ],
            "url": {
              "raw": "{{base_url}}/cart",
              "host": [
                "{{base_url}}"
              ],
              "path": [
                "cart"
              ]
            }
          },
          "response": []
        },
        {
          "name": "Add To Cart",
          "request": {
            "method": "POST",
            "header": [
              {
                "key": "Authorization",
                "value": "Bearer {{auth_token}}"
              }
            ],
            "body": {
              "mode": "raw",
              "raw": "{\n  \"productId\": \"some_product_id\",\n  \"quantity\": 1\n}",
              "options": {
                "raw": {
                  "language": "json"
                }
              }
            },
            "url": {
              "raw": "{{base_url}}/cart",
              "host": [
                "{{base_url}}"
              ],
              "path": [
                "cart"
              ]
            }
          },
          "response": []
        },
        {
          "name": "Update Cart Item",
          "request": {
            "method": "PATCH",
            "header": [
              {
                "key": "Authorization",
                "value": "Bearer {{auth_token}}"
              }
            ],
            "body": {
              "mode": "raw",
              "raw": "{\n  \"quantity\": 2\n}",
              "options": {
                "raw": {
                  "language": "json"
                }
              }
            },
            "url": {
              "raw": "{{base_url}}/cart/some_product_id",
              "host": [
                "{{base_url}}"
              ],
              "path": [
                "cart",
                "some_product_id"
              ]
            }
          },
          "response": []
        },
        {
          "name": "Remove From Cart",
          "request": {
            "method": "DELETE",
            "header": [
              {
                "key": "Authorization",
                "value": "Bearer {{auth_token}}"
              }
            ],
            "url": {
              "raw": "{{base_url}}/cart/some_product_id",
              "host": [
                "{{base_url}}"
              ],
              "path": [
                "cart",
                "some_product_id"
              ]
            }
          },
          "response": []
        }
      ]
    },
    {
      "name": "Category",
      "item": [
        {
          "name": "Create Category",
          "request": {
            "method": "POST",
            "header": [],
            "body": {
              "mode": "raw",
              "raw": "{\n  \"name\": \"New Category\",\n  \"description\": \"A new category for books.\"\n}",
              "options": {
                "raw": {
                  "language": "json"
                }
              }
            },
            "url": {
              "raw": "{{base_url}}/category",
              "host": [
                "{{base_url}}"
              ],
              "path": [
                "category"
              ]
            }
          },
          "response": []
        },
        {
          "name": "Get All Categories",
          "request": {
            "method": "GET",
            "header": [],
            "url": {
              "raw": "{{base_url}}/category",
              "host": [
                "{{base_url}}"
              ],
              "path": [
                "category"
              ]
            }
          },
          "response": []
        },
        {
          "name": "Get Category By Id",
          "request": {
            "method": "GET",
            "header": [],
            "url": {
              "raw": "{{base_url}}/category/some_category_id",
              "host": [
                "{{base_url}}"
              ],
              "path": [
                "category",
                "some_category_id"
              ]
            }
          },
          "response": []
        },
        {
          "name": "Update Category",
          "request": {
            "method": "PUT",
            "header": [],
            "body": {
              "mode": "raw",
              "raw": "{\n  \"name\": \"Updated Category Name\"\n}",
              "options": {
                "raw": {
                  "language": "json"
                }
              }
            },
            "url": {
              "raw": "{{base_url}}/category/some_category_id",
              "host": [
                "{{base_url}}"
              ],
              "path": [
                "category",
                "some_category_id"
              ]
            }
          },
          "response": []
        },
        {
          "name": "Delete Category",
          "request": {
            "method": "DELETE",
            "header": [],
            "url": {
              "raw": "{{base_url}}/category/some_category_id",
              "host": [
                "{{base_url}}"
              ],
              "path": [
                "category",
                "some_category_id"
              ]
            }
          },
          "response": []
        }
      ]
    },
    {
      "name": "Order",
      "item": [
        {
          "name": "Create Order",
          "request": {
            "method": "POST",
            "header": [
              {
                "key": "Authorization",
                "value": "Bearer {{auth_token}}"
              }
            ],
            "body": {
              "mode": "raw",
              "raw": "{\n  \"shippingAddress\": \"123 Main St\",\n  \"paymentMethod\": \"Credit Card\"\n}",
              "options": {
                "raw": {
                  "language": "json"
                }
              }
            },
            "url": {
              "raw": "{{base_url}}/order",
              "host": [
                "{{base_url}}"
              ],
              "path": [
                "order"
              ]
            }
          },
          "response": []
        },
        {
          "name": "Get My Orders",
          "request": {
            "method": "GET",
            "header": [
              {
                "key": "Authorization",
                "value": "Bearer {{auth_token}}"
              }
            ],
            "url": {
              "raw": "{{base_url}}/order/my-orders",
              "host": [
                "{{base_url}}"
              ],
              "path": [
                "order",
                "my-orders"
              ]
            }
          },
          "response": []
        },
        {
          "name": "Get Order By Id",
          "request": {
            "method": "GET",
            "header": [
              {
                "key": "Authorization",
                "value": "Bearer {{auth_token}}"
              }
            ],
            "url": {
              "raw": "{{base_url}}/order/some_order_id",
              "host": [
                "{{base_url}}"
              ],
              "path": [
                "order",
                "some_order_id"
              ]
            }
          },
          "response": []
        },
        {
          "name": "Get All Orders (Admin)",
          "request": {
            "method": "GET",
            "header": [
              {
                "key": "Authorization",
                "value": "Bearer {{auth_token}}"
              }
            ],
            "url": {
              "raw": "{{base_url}}/order/admin",
              "host": [
                "{{base_url}}"
              ],
              "path": [
                "order",
                "admin"
              ]
            }
          },
          "response": []
        },
        {
          "name": "Update Order Status (Admin)",
          "request": {
            "method": "PATCH",
            "header": [
              {
                "key": "Authorization",
                "value": "Bearer {{auth_token}}"
              }
            ],
            "body": {
              "mode": "raw",
              "raw": "{\n  \"status\": \"Shipped\"\n}",
              "options": {
                "raw": {
                  "language": "json"
                }
              }
            },
            "url": {
              "raw": "{{base_url}}/order/admin/some_order_id",
              "host": [
                "{{base_url}}"
              ],
              "path": [
                "order",
                "admin",
                "some_order_id"
              ]
            }
          },
          "response": []
        }
      ]
    },
    {
      "name": "Product",
      "item": [
        {
          "name": "Create Product",
          "request": {
            "method": "POST",
            "header": [],
            "body": {
              "mode": "raw",
              "raw": "{\n  \"name\": \"New Book\",\n  \"price\": 19.99,\n  \"description\": \"An exciting new book.\",\n  \"categoryId\": \"some_category_id\",\n  \"authors\": [{ \"name\": \"Author Name\" }],\n  \"inStock\": 100\n}",
              "options": {
                "raw": {
                  "language": "json"
                }
              }
            },
            "url": {
              "raw": "{{base_url}}/product",
              "host": [
                "{{base_url}}"
              ],
              "path": [
                "product"
              ]
            }
          },
          "response": []
        },
        {
          "name": "Get All Products",
          "request": {
            "method": "GET",
            "header": [],
            "url": {
              "raw": "{{base_url}}/product",
              "host": [
                "{{base_url}}"
              ],
              "path": [
                "product"
              ]
            }
          },
          "response": []
        },
        {
          "name": "Get Product By Id",
          "request": {
            "method": "GET",
            "header": [],
            "url": {
              "raw": "{{base_url}}/product/some_product_id",
              "host": [
                "{{base_url}}"
              ],
              "path": [
                "product",
                "some_product_id"
              ]
            }
          },
          "response": []
        },
        {
          "name": "Update Product",
          "request": {
            "method": "PUT",
            "header": [],
            "body": {
              "mode": "raw",
              "raw": "{\n  \"name\": \"Updated Book Name\"\n}",
              "options": {
                "raw": {
                  "language": "json"
                }
              }
            },
            "url": {
              "raw": "{{base_url}}/product/some_product_id",
              "host": [
                "{{base_url}}"
              ],
              "path": [
                "product",
                "some_product_id"
              ]
            }
          },
          "response": []
        },
        {
          "name": "Delete Product",
          "request": {
            "method": "DELETE",
            "header": [],
            "url": {
              "raw": "{{base_url}}/product/some_product_id",
              "host": [
                "{{base_url}}"
              ],
              "path": [
                "product",
                "some_product_id"
              ]
            }
          },
          "response": []
        }
      ]
    },
    {
      "name": "Review",
      "item": [
        {
          "name": "Create Review",
          "request": {
            "method": "POST",
            "header": [],
            "body": {
              "mode": "raw",
              "raw": "{\n  \"productId\": \"some_product_id\",\n  \"rating\": 5,\n  \"comment\": \"This book was amazing!\"\n}",
              "options": {
                "raw": {
                  "language": "json"
                }
              }
            },
            "url": {
              "raw": "{{base_url}}/review",
              "host": [
                "{{base_url}}"
              ],
              "path": [
                "review"
              ]
            }
          },
          "response": []
        },
        {
          "name": "Get Reviews By Product",
          "request": {
            "method": "GET",
            "header": [],
            "url": {
              "raw": "{{base_url}}/review/product/some_product_id",
              "host": [
                "{{base_url}}"
              ],
              "path": [
                "review",
                "product",
                "some_product_id"
              ]
            }
          },
          "response": []
        },
        {
          "name": "Delete Review",
          "request": {
            "method": "DELETE",
            "header": [],
            "url": {
              "raw": "{{base_url}}/review/some_review_id",
              "host": [
                "{{base_url}}"
              ],
              "path": [
                "review",
                "some_review_id"
              ]
            }
          },
          "response": []
        }
      ]
    },
    {
      "name": "Test",
      "item": [
        {
          "name": "Test Protect Middleware",
          "request": {
            "method": "GET",
            "header": [
              {
                "key": "Authorization",
                "value": "Bearer {{auth_token}}"
              }
            ],
            "url": {
              "raw": "{{base_url}}/test",
              "host": [
                "{{base_url}}"
              ],
              "path": [
                "test"
              ]
            }
          },
          "response": []
        }
      ]
    }
  ]
}